seizcord.py
seizcord-0.0.5.dist-info/LICENSE
seizcord-0.0.5.dist-info/METADATA
seizcord-0.0.5.dist-info/WHEEL
seizcord-0.0.5.dist-info/top_level.txt
seizcord-0.0.5.dist-info/RECORD
