Metadata-Version: 2.1
Name: seizcord
Version: 0.0.5
Summary: seizcord is a python library using discord api
Author: uhq.s
Project-URL: Homepage, https://github.com/seized0/seizcord
Project-URL: Issues, https://github.com/seized0/
Classifier: Programming Language :: Python :: 3
Classifier: License :: OSI Approved :: MIT License
Classifier: Operating System :: OS Independent
Requires-Python: >=3.9
License-File: LICENSE
